p2pnetwork/__init__.py
p2pnetwork/node.py
p2pnetwork/nodeconnection.py
p2pnetwork/tests/__init__.py
p2pnetwork/tests/test_node.py
p2pnetwork/tests/test_nodeconnection.py
p2pnetwork-1.0.dist-info/LICENSE
p2pnetwork-1.0.dist-info/METADATA
p2pnetwork-1.0.dist-info/WHEEL
p2pnetwork-1.0.dist-info/top_level.txt
p2pnetwork-1.0.dist-info/RECORD
