Metadata-Version: 2.1
Name: p2pnetwork
Version: 1.0
Summary: Python decentralized peer-to-peer network application framework.
Home-page: https://github.com/macsnoeren/python-p2p-network
Author: Maurice Snoeren
Author-email: macsnoeren@gmail.com
License: UNKNOWN
Platform: UNKNOWN
Classifier: Programming Language :: Python :: 3
Classifier: License :: OSI Approved :: GNU General Public License v3 (GPLv3)
Classifier: Operating System :: OS Independent
Requires-Python: >=3.6
